Workbook

Sheet BASE
A1: Episódios do NerdCast: | B1: Link | C1: Data | D1: Dia | E1: Mês | F1: Ano | G1: DT Data | H1: Data Semana | I1: Tipo + Episódio | J1: Tipo | K1: # Episódio | L1: Dif Data
A2: Título: NerdCast 01 - Super-Homem: Herói americano ou do mundo? - | B2: https://jovemnerd.com.br/nerdcast/01-super-homem-heroi-americando-ou-do-mundo/ | C2: Sun, 02 Apr 2006 17:39:39 +0000 | D2: 02 | E2: 4 | F2: 2006 | G2: 38809 | H2: 1 | I2: NerdCast 01 | J2: NerdCast | K2: 01
A3: Título: NerdCast 02 - Batman Continues: Quem serão os vilões? - | B3: https://jovemnerd.com.br/nerdcast/02-batman-continues-quem-serao-os-viloes/ | C3: Sun, 02 Apr 2006 17:43:22 +0000 | D3: 02 | E3: 4 | F3: 2006 | G3: 38809 | H3: 1 | I3: NerdCast 02 | J3: NerdCast | K3: 02 | L3: =G3-G2 -> 0
A4: Título: NerdCast 03 - Quadrinhos: A volta de Jason Todd (?!) - | B4: https://jovemnerd.com.br/nerdcast/03-quadrinhos-a-volta-de-jason-todd/ | C4: Sun, 02 Apr 2006 17:46:32 +0000 | D4: 02 | E4: 4 | F4: 2006 | G4: 38809 | H4: 1 | I4: NerdCast 03 | J4: NerdCast | K4: 03 | L4: =G4-G3 -> 0
A5: Título: NerdCast 04 - Rocky Balboa está de volta: comemorar ou chorar? - | B5: https://jovemnerd.com.br/nerdcast/04-rocky-balboa-esta-de-volta-comemorar-ou-chorar/ | C5: Sun, 02 Apr 2006 17:47:44 +0000 | D5: 02 | E5: 4 | F5: 2006 | G5: 38809 | H5: 1 | I5: NerdCast 04 | J5: NerdCast | K5: 04 | L5: =G5-G4 -> 0
A6: Título: NerdCast 05 - Bárbaros, Exterminadores e uma Vareta Espacial - | B6: https://jovemnerd.com.br/nerdcast/nerdcast-05-barbaros-exterminadores-e-uma-vareta-espacial/ | C6: Sun, 02 Apr 2006 19:19:01 +0000 | D6: 02 | E6: 4 | F6: 2006 | G6: 38809 | H6: 1 | I6: NerdCast 05 | J6: NerdCast | K6: 05 | L6: =G6-G5 -> 0
A7: Título: NerdCast 06 - V de Vingança - | B7: https://jovemnerd.com.br/nerdcast/nerdcast-06-v-de-vinganca/ | C7: Sat, 08 Apr 2006 17:11:14 +0000 | D7: 08 | E7: 4 | F7: 2006 | G7: 38815 | H7: 7 | I7: NerdCast 06 | J7: NerdCast | K7: 06 | L7: =G7-G6 -> 6
A8: Título: NerdCast 07 - Os brucutus dos anos 80 - | B8: https://jovemnerd.com.br/nerdcast/nerdcast-07-os-brucutus-dos-anos-80/ | C8: Tue, 11 Apr 2006 01:32:49 +0000 | D8: 11 | E8: 4 | F8: 2006 | G8: 38818 | H8: 3 | I8: NerdCast 07 | J8: NerdCast | K8: 07 | L8: =G8-G7 -> 3
A9: Título: NerdCast 08 - O Poderoso Chefão - | B9: https://jovemnerd.com.br/nerdcast/nerdcast-08-o-poderoso-chefao/ | C9: Tue, 18 Apr 2006 00:57:31 +0000 | D9: 18 | E9: 4 | F9: 2006 | G9: 38825 | H9: 3 | I9: NerdCast 08 | J9: NerdCast | K9: 08 | L9: =G9-G8 -> 7
A10: Título: NerdCast 09 - Pérolas do RPG - | B10: https://jovemnerd.com.br/nerdcast/nerdcast-09-perolas-do-rpg/ | C10: Fri, 21 Apr 2006 14:15:39 +0000 | D10: 21 | E10: 4 | F10: 2006 | G10: 38828 | H10: 6 | I10: NerdCast 09 | J10: NerdCast | K10: 09 | L10: =G10-G9 -> 3
A11: Título: NerdCast 10 - Nostalgia Tecnológica - | B11: https://jovemnerd.com.br/nerdcast/nerdcast-10-nostalgia-tecnologica/ | C11: Fri, 28 Apr 2006 03:24:55 +0000 | D11: 28 | E11: 4 | F11: 2006 | G11: 38835 | H11: 6 | I11: NerdCast 10 | J11: NerdCast | K11: 10 | L11: =G11-G10 -> 7
A12: Título: NerdCast 11 - Missão: Nerdcast - | B12: https://jovemnerd.com.br/nerdcast/nerdcast-11-missao-nerdcast/ | C12: Sun, 07 May 2006 23:44:26 +0000 | D12: 07 | E12: 5 | F12: 2006 | G12: 38844 | H12: 1 | I12: NerdCast 11 | J12: NerdCast | K12: 11 | L12: =G12-G11 -> 9
A13: Título: NerdCast 12 - Os primórdios dos vídeo games - | B13: https://jovemnerd.com.br/nerdcast/nerdcast-12-os-primordios-dos-video-games/ | C13: Thu, 11 May 2006 02:19:04 +0000 | D13: 11 | E13: 5 | F13: 2006 | G13: 38848 | H13: 5 | I13: NerdCast 12 | J13: NerdCast | K13: 12 | L13: =G13-G12 -> 4
A14: Título: NerdCast 13 - Google é meu pastor e nada me faltará - | B14: https://jovemnerd.com.br/nerdcast/nerdcast-13-google-e-meu-pastor-e-nada-me-faltara/ | C14: Wed, 17 May 2006 01:47:02 +0000 | D14: 17 | E14: 5 | F14: 2006 | G14: 38854 | H14: 4 | I14: NerdCast 13 | J14: NerdCast | K14: 13 | L14: =G14-G13 -> 6
... A520: Título: NerdCast 494 - Desista da Dieta - | B520: https://jovemnerd.com.br/nerdcast/nerdcast-494-desista-da-dieta/ | C520: Fri, 04 Dec 2015 02:37:43 +0000 | D520: 04 | E520: 12 | F520: 2015 | G520: 42342 | H520: 6 | I520: NerdCast 494 | J520: NerdCast | K520: 494 | L520: =G520-G519 -> 7
A521: Título: HaloCast Oferecido por Xbox - HaloCast 1 - | B521: https://jovemnerd.com.br/nerdcast/extra/halocast-1/ | C521: Fri, 11 Dec 2015 17:37:11 +0000 | D521: 11 | E521: 12 | F521: 2015 | G521: 42349 | H521: 6 | I521: HaloCast Oferecido por Xbox | J521: HaloCast Oferecido por Xbox | L521: =G521-G520 -> 7
A522: Título: NerdCast 495 - A Revolução Star Wars - | B522: https://jovemnerd.com.br/nerdcast/nerdcast-495-a-revolucao-star-wars/ | C522: Fri, 11 Dec 2015 11:30:23 +0000 | D522: 11 | E522: 12 | F522: 2015 | G522: 42349 | H522: 6 | I522: NerdCast 495 | J522: NerdCast | K522: 495 | L522: =G522-G521 -> 0
A523: Título: HaloCast Oferecido por Xbox - HaloCast 2 - | B523: https://jovemnerd.com.br/nerdcast/extra/halocast-2/ | C523: Thu, 17 Dec 2015 18:54:46 +0000 | D523: 17 | E523: 12 | F523: 2015 | G523: 42355 | H523: 5 | I523: HaloCast Oferecido por Xbox | J523: HaloCast Oferecido por Xbox | L523: =G523-G522 -> 6
A524: Título: Empreendedor 12 - A vida depois da venda - | B524: https://jovemnerd.com.br/nerdcast/empreendedor/nerdcast-empreendedor-12-a-vida-depois-da-venda/ | C524: Fri, 18 Dec 2015 09:07:47 +0000 | D524: 18 | E524: 12 | F524: 2015 | G524: 42356 | H524: 6 | I524: Empreendedor 12 | J524: Empreendedor | K524: 12 | L524: =G524-G523 -> 1
A525: Título: NerdCast 496 - Uma viajante no Oriente Médio - | B525: https://jovemnerd.com.br/nerdcast/nerdcast-496-uma-viajante-no-oriente-medio/ | C525: Fri, 18 Dec 2015 09:08:28 +0000 | D525: 18 | E525: 12 | F525: 2015 | G525: 42356 | H525: 6 | I525: NerdCast 496 | J525: NerdCast | K525: 496 | L525: =G525-G524 -> 0
A526: Título: HaloCast Oferecido por Xbox - HaloCast 3 - | B526: https://jovemnerd.com.br/nerdcast/extra/halocast-3/ | C526: Tue, 22 Dec 2015 13:33:04 +0000 | D526: 22 | E526: 12 | F526: 2015 | G526: 42360 | H526: 3 | I526: HaloCast Oferecido por Xbox | J526: HaloCast Oferecido por Xbox | L526: =G526-G525 -> 4
A527: Título: NerdCast 497 - Star Wars VII – O despertar das emoções - | B527: https://jovemnerd.com.br/nerdcast/nerdcast-497-star-wars-vii-o-despertar-das-emocoes/ | C527: Fri, 25 Dec 2015 00:01:59 +0000 | D527: 25 | E527: 12 | F527: 2015 | G527: 42363 | H527: 6 | I527: NerdCast 497 | J527: NerdCast | K527: 497 | L527: =G527-G526 -> 3
A528: Título: NerdCast RPG 498 - RPG Cyberpunk 3: Estrada para o inferno - | B528: https://jovemnerd.com.br/nerdcast/nerdcast-498-rpg-cyberpunk-3-estrada-para-o-inferno/ | C528: Fri, 08 Jan 2016 22:08:39 +0000 | D528: 08 | E528: 1 | F528: 2016 | G528: 42377 | H528: 6 | I528: NerdCast RPG 498 | J528: NerdCast RPG | K528: 498 | L528: =G528-G527 -> 14
A529: Título: NerdCast 499 - Bandas de Garagem - | B529: https://jovemnerd.com.br/nerdcast/nerdcast-499-bandas-de-garagem/ | C529: Fri, 15 Jan 2016 07:04:47 +0000 | D529: 15 | E529: 1 | F529: 2016 | G529: 42384 | H529: 6 | I529: NerdCast 499 | J529: NerdCast | K529: 499 | L529: =G529-G528 -> 7
A530: Título: NerdCast 500 - O Melhor de 500 Nerdcasts! - | B530: https://jovemnerd.com.br/nerdcast/nerdcast-500-o-melhor-de-500-nerdcasts/ | C530: Fri, 22 Jan 2016 12:57:06 +0000 | D530: 22 | E530: 1 | F530: 2016 | G530: 42391 | H530: 6 | I530: NerdCast 500 | J530: NerdCast | K530: 500 | L530: =G530-G529 -> 7
A531: Título: Empreendedor 13 - Empreendedorismo Digital - | B531: https://jovemnerd.com.br/nerdcast/empreendedor/nerdcast-empreendedor-13-empreendedorismo-digital/ | C531: Fri, 29 Jan 2016 09:30:50 +0000 | D531: 29 | E531: 1 | F531: 2016 | G531: 42398 | H531: 6 | I531: Empreendedor 13 | J531: Empreendedor | K531: 13 | L531: =G531-G530 -> 7
A532: Título: NerdCast 501 - Pega na mentira! - | B532: https://jovemnerd.com.br/nerdcast/nerdcast-501-pega-na-mentira/ | C532: Fri, 29 Jan 2016 09:31:12 +0000 | D532: 29 | E532: 1 | F532: 2016 | G532: 42398 | H532: 6 | I532: NerdCast 501 | J532: NerdCast | K532: 501 | L532: =G532-G531 -> 0
A533: Título: NerdCast 502 - A moderna monarquia britânica - | B533: https://jovemnerd.com.br/nerdcast/nerdcast-502-a-moderna-monarquia-britanica/ | C533: Fri, 05 Feb 2016 00:38:20 +0000 | D533: 05 | E533: 2 | F533: 2016 | G533: 42405 | H533: 6 | I533: NerdCast 502 | J533: NerdCast | K533: 502 | L533: =G533-G532 -> 7
A534: Título: NerdCast 503 - Esse Zika é vírus! - | B534: https://jovemnerd.com.br/nerdcast/nerdcast-503-esse-zika-e-virus/ | C534: Thu, 11 Feb 2016 23:01:12 +0000 | D534: 11 | E534: 2 | F534: 2016 | G534: 42411 | H534: 5 | I534: NerdCast 503 | J534: NerdCast | K534: 503 | L534: =G534-G533 -> 6
A535: Título: NerdCast 504 - Comfort Food - | B535: https://jovemnerd.com.br/nerdcast/nerdcast-504-comfort-food/ | C535: Thu, 18 Feb 2016 23:06:12 +0000 | D535: 18 | E535: 2 | F535: 2016 | G535: 42418 | H535: 5 | I535: NerdCast 504 | J535: NerdCast | K535: 504 | L535: =G535-G534 -> 7
A536: Título: Empreendedor 14 - Empreendendo entre gigantes - | B536: https://jovemnerd.com.br/nerdcast/empreendedor/nerdcast-empreendedor-14-empreendendo-entre-gigantes/ | C536: Fri, 26 Feb 2016 09:44:04 +0000 | D536: 26 | E536: 2 | F536: 2016 | G536: 42426 | H536: 6 | I536: Empreendedor 14 | J536: Empreendedor | K536: 14 | L536: =G536-G535 -> 8
A537: Título: NerdCast 505 - Doctor… Who? - | B537: https://jovemnerd.com.br/nerdcast/nerdcast-505-doctor-who/ | C537: Fri, 26 Feb 2016 09:44:44 +0000 | D537: 26 | E537: 2 | F537: 2016 | G537: 42426 | H537: 6 | I537: NerdCast 505 | J537: NerdCast | K537: 505 | L537: =G537-G536 -> 0
A538: Título: NerdCast 506 - Cegos, nerds e loucos 2 - | B538: https://jovemnerd.com.br/nerdcast/nerdcast-506-cegos-nerds-e-loucos-2/ | C538: Fri, 04 Mar 2016 10:22:04 +0000 | D538: 04 | E538: 3 | F538: 2016 | G538: 42433 | H538: 6 | I538: NerdCast 506 | J538: NerdCast | K538: 506 | L538: =G538-G537 -> 7
... A636: Título: NerdCast 572 - A origem da vida - | B636: https://jovemnerd.com.br/nerdcast/origem-da-vida/ | C636: Fri, 16 Jun 2017 11:00:27 +0000 | D636: 16 | E636: 6 | F636: 2017 | G636: 42902 | H636: 6 | I636: NerdCast 572 | J636: NerdCast | K636: 572 | L636: =G636-G635 -> 7
A637: Título: Extra Oferecido por GE - Indústrias Superpoderosas - | B637: https://jovemnerd.com.br/nerdcast/extra/nerdcast-ge-industrias-superpoderosas/ | C637: Fri, 23 Jun 2017 11:00:07 +0000 | D637: 23 | E637: 6 | F637: 2017 | G637: 42909 | H637: 6 | I637: Extra Oferecido por GE | J637: Extra Oferecido por GE | L637: =G637-G636 -> 7
A638: Título: NerdCast 573 - Momentos Sublimes - | B638: https://jovemnerd.com.br/nerdcast/momentos-sublimes/ | C638: Fri, 23 Jun 2017 11:01:35 +0000 | D638: 23 | E638: 6 | F638: 2017 | G638: 42909 | H638: 6 | I638: NerdCast 573 | J638: NerdCast | K638: 573 | L638: =G638-G637 -> 0
A639: Título: Empreendedor 30 - Visão, coragem e competência - | B639: https://jovemnerd.com.br/nerdcast/empreendedor/visao-coragem-e-competencia/ | C639: Fri, 30 Jun 2017 11:00:14 +0000 | D639: 30 | E639: 6 | F639: 2017 | G639: 42916 | H639: 6 | I639: Empreendedor 30 | J639: Empreendedor | K639: 30 | L639: =G639-G638 -> 7
A640: Título: NerdCast 574 - A Reforma Protestante - | B640: https://jovemnerd.com.br/nerdcast/a-reforma-protestante/ | C640: Fri, 30 Jun 2017 11:01:37 +0000 | D640: 30 | E640: 6 | F640: 2017 | G640: 42916 | H640: 6 | I640: NerdCast 574 | J640: NerdCast | K640: 574 | L640: =G640-G639 -> 0
A641: Título: NerdCast 575 - Nossa língua portuguesa - | B641: https://jovemnerd.com.br/nerdcast/nossa-lingua-portuguesa/ | C641: Fri, 07 Jul 2017 11:01:00 +0000 | D641: 07 | E641: 7 | F641: 2017 | G641: 42923 | H641: 6 | I641: NerdCast 575 | J641: NerdCast | K641: 575 | L641: =G641-G640 -> 7
A642: Título: NerdTech 17 - Aprendizado Online - | B642: https://jovemnerd.com.br/nerdcast/nerdtech/aprendizado-online/ | C642: Fri, 07 Jul 2017 11:00:15 +0000 | D642: 07 | E642: 7 | F642: 2017 | G642: 42923 | H642: 6 | I642: NerdTech 17 | J642: NerdTech | K642: 17 | L642: =G642-G641 -> 0
A643: Título: NerdCast 576 - Aquele Tipinho de Pessoa 2 - | B643: https://jovemnerd.com.br/nerdcast/aquele-tipinho-de-pessoa-2/ | C643: Fri, 14 Jul 2017 11:00:15 +0000 | D643: 14 | E643: 7 | F643: 2017 | G643: 42930 | H643: 6 | I643: NerdCast 576 | J643: NerdCast | K643: 576 | L643: =G643-G642 -> 7
A644: Título: NerdCast 577 - Fama, pra que te quero? - | B644: https://jovemnerd.com.br/nerdcast/fama-pra-que-te-quero/ | C644: Fri, 21 Jul 2017 11:00:35 +0000 | D644: 21 | E644: 7 | F644: 2017 | G644: 42937 | H644: 6 | I644: NerdCast 577 | J644: NerdCast | K644: 577 | L644: =G644-G643 -> 7
A645: Título: Empreendedor 31 - Branding e construção de marca - | B645: https://jovemnerd.com.br/nerdcast/empreendedor/branding-e-construcao-de-marca/ | C645: Fri, 28 Jul 2017 11:00:16 +0000 | D645: 28 | E645: 7 | F645: 2017 | G645: 42944 | H645: 6 | I645: Empreendedor 31 | J645: Empreendedor | K645: 31 | L645: =G645-G644 -> 7
A646: Título: NerdCast 578 - Dunkirk – A paradinha do Reich - | B646: https://jovemnerd.com.br/nerdcast/dunkirk-paradinha-do-reich/ | C646: Fri, 28 Jul 2017 11:01:28 +0000 | D646: 28 | E646: 7 | F646: 2017 | G646: 42944 | H646: 6 | I646: NerdCast 578 | J646: NerdCast | K646: 578 | L646: =G646-G645 -> 0
A647: Título: NerdCast 579 - Brincadeira de Criança 2 - | B647: https://jovemnerd.com.br/nerdcast/brincadeira-de-crianca-2/ | C647: Fri, 04 Aug 2017 11:01:00 +0000 | D647: 04 | E647: 8 | F647: 2017 | G647: 42951 | H647: 6 | I647: NerdCast 579 | J647: NerdCast | K647: 579 | L647: =G647-G646 -> 7
A648: Título: NerdTech 18 - Metodologias ágeis - | B648: https://jovemnerd.com.br/nerdcast/nerdtech/metodologias-ageis/ | C648: Fri, 04 Aug 2017 11:00:36 +0000 | D648: 04 | E648: 8 | F648: 2017 | G648: 42951 | H648: 6 | I648: NerdTech 18 | J648: NerdTech | K648: 18 | L648: =G648-G647 -> 0
A649: Título: NerdCast 580 - Road Trip - | B649: https://jovemnerd.com.br/nerdcast/road-trip/ | C649: Fri, 11 Aug 2017 11:00:20 +0000 | D649: 11 | E649: 8 | F649: 2017 | G649: 42958 | H649: 6 | I649: NerdCast 580 | J649: NerdCast | K649: 580 | L649: =G649-G648 -> 7
... A690: Título: Empreendedor 38 - Muito além do marketing - | B690: https://jovemnerd.com.br/nerdcast/empreendedor/muito-alem-do-marketing/ | C690: Fri, 23 Feb 2018 11:01:15 +0000 | D690: 23 | E690: 2 | F690: 2018 | G690: 43154 | H690: 6 | I690: Empreendedor 38 | J690: Empreendedor | K690: 38 | L690: =G690-G689 -> 7
A691: Título: Extra Oferecido por Petrobras - NerdLab Petrobras - | B691: https://jovemnerd.com.br/nerdcast/extra/nerdlab-petrobras/ | C691: Fri, 23 Feb 2018 11:00:25 +0000 | D691: 23 | E691: 2 | F691: 2018 | G691: 43154 | H691: 6 | I691: Extra Oferecido por Petrobras | J691: Extra Oferecido por Petrobras | L691: =G691-G690 -> 0
A692: Título: NerdCast 608 - Punisheiro fez justiça? - | B692: https://jovemnerd.com.br/nerdcast/punisher-justriceiro-netflix-nerdcast-punisheiro-fez-justica/ | C692: Fri, 23 Feb 2018 11:02:35 +0000 | D692: 23 | E692: 2 | F692: 2018 | G692: 43154 | H692: 6 | I692: NerdCast 608 | J692: NerdCast | K692: 608 | L692: =G692-G691 -> 0
A693: Título: NerdCast 609 - Nerdcast sem Fio 4 - | B693: https://jovemnerd.com.br/nerdcast/nerdcast-sem-fio-4/ | C693: Fri, 02 Mar 2018 11:01:31 +0000 | D693: 02 | E693: 3 | F693: 2018 | G693: 43161 | H693: 6 | I693: NerdCast 609 | J693: NerdCast | K693: 609 | L693: =G693-G692 -> 7
A694: Título: NerdTech 25 - Ferramentas de produtividade - | B694: https://jovemnerd.com.br/nerdcast/nerdtech/ferramentas-de-produtividade/ | C694: Fri, 02 Mar 2018 11:00:30 +0000 | D694: 02 | E694: 3 | F694: 2018 | G694: 43161 | H694: 6 | I694: NerdTech 25 | J694: NerdTech | K694: 25 | L694: =G694-G693 -> 0
A695: Título: NerdCast 610 - Pantera Negra: Afrofuturismo representado - | B695: https://jovemnerd.com.br/nerdcast/pantera-negra-afrofuturismo-representado/ | C695: Fri, 09 Mar 2018 11:00:45 +0000 | D695: 09 | E695: 3 | F695: 2018 | G695: 43168 | H695: 6 | I695: NerdCast 610 | J695: NerdCast | K695: 610 | L695: =G695-G694 -> 7
A696: Título: NerdCast 611 - Histórias Desgraçadas - | B696: https://jovemnerd.com.br/nerdcast/historias-desgracadas/ | C696: Fri, 16 Mar 2018 11:01:16 +0000 | D696: 16 | E696: 3 | F696: 2018 | G696: 43175 | H696: 6 | I696: NerdCast 611 | J696: NerdCast | K696: 611 | L696: =G696-G695 -> 7
A697: Título: Speak English 02 - Traduções absurdas - | B697: https://jovemnerd.com.br/nerdcast/speak-english/traducoes-absurdas/ | C697: Fri, 16 Mar 2018 11:00:40 +0000 | D697: 16 | E697: 3 | F697: 2018 | G697: 43175 | H697: 6 | I697: Speak English 02 | J697: Speak English | K697: 02 | L697: =G697-G696 -> 0
A698: Título: NerdCast 612 - Blockchain, criptomoedas e lagosta - | B698: https://jovemnerd.com.br/nerdcast/blockchain-criptomoedas-e-lagosta/ | C698: Fri, 23 Mar 2018 11:00:36 +0000 | D698: 23 | E698: 3 | F698: 2018 | G698: 43182 | H698: 6 | I698: NerdCast 612 | J698: NerdCast | K698: 612 | L698: =G698-G697 -> 7
A699: Título: Empreendedor 39 - A vitória do Orlando City - | B699: https://jovemnerd.com.br/nerdcast/empreendedor/vitoria-do-orlando-city/ | C699: Fri, 30 Mar 2018 10:21:16 +0000 | D699: 30 | E699: 3 | F699: 2018 | G699: 43189 | H699: 6 | I699: Empreendedor 39 | J699: Empreendedor | K699: 39 | L699: =G699-G698 -> 7
A700: Título: NerdCast 613 - Especialistas de porra nenhuma - | B700: https://jovemnerd.com.br/nerdcast/especialistas-de-porra-penhuma/ | C700: Fri, 30 Mar 2018 10:22:14 +0000 | D700: 30 | E700: 3 | F700: 2018 | G700: 43189 | H700: 6 | I700: NerdCast 613 | J700: NerdCast | K700: 613 | L700: =G700-G699 -> 0
A701: Título: NerdCast 614 - Dormindo no ponto - | B701: https://jovemnerd.com.br/nerdcast/dormindo-no-ponto/ | C701: Fri, 06 Apr 2018 11:01:58 +0000 | D701: 06 | E701: 4 | F701: 2018 | G701: 43196 | H701: 6 | I701: NerdCast 614 | J701: NerdCast | K701: 614 | L701: =G701-G700 -> 7
A702: Título: NerdTech 26 - Breve história da Apple - | B702: https://jovemnerd.com.br/nerdcast/nerdtech/breve-historia-da-apple/ | C702: Fri, 06 Apr 2018 11:00:38 +0000 | D702: 06 | E702: 4 | F702: 2018 | G702: 43196 | H702: 6 | I702: NerdTech 26 | J702: NerdTech | K702: 26 | L702: =G702-G701 -> 0
A703: Título: NerdCast 615 - E se o Brasil fosse colonizado por outras potências? - | B703: https://jovemnerd.com.br/nerdcast/e-se-o-brasil-fosse-colonizado-por-outras-potencias/ | C703: Fri, 13 Apr 2018 11:00:20 +0000 | D703: 13 | E703: 4 | F703: 2018 | G703: 43203 | H703: 6 | I703: NerdCast 615 | J703: NerdCast | K703: 615 | L703: =G703-G702 -> 7
... A1106: Título: Lá do Bunker 13 - O trem do hype - | B1106: https://jovemnerd.com.br/nerdcast/la-do-bunker/o-trem-do-hype/ | C1106: Mon, 25 Oct 2021 06:00:09 +0000 | D1106: 25 | E1106: 10 | F1106: 2021 | G1106: 44494 | H1106: 2 | I1106: Lá do Bunker 13 | J1106: Lá do Bunker | K1106: 13 | L1106: =G1106-G1105 -> 2
A1107: Título: Extra Oferecido por Avanade - O consultor, o chupa-cabra e o fantasma do Hi-Tech - | B1107: https://jovemnerd.com.br/nerdcast/extra/o-consultor-o-chupa-cabra-e-o-fantasma-do-hi-tech/ | C1107: Tue, 26 Oct 2021 11:54:54 +0000 | D1107: 26 | E1107: 10 | F1107: 2021 | G1107: 44495 | H1107: 3 | I1107: Extra Oferecido por Avanade | J1107: Extra Oferecido por Avanade | L1107: =G1107-G1106 -> 1
A1108: Título: Empreendedor 81 - Plataformas digitais e na vida real - | B1108: https://jovemnerd.com.br/nerdcast/empreendedor/plataformas-digitais-e-na-vida-real/ | C1108: Fri, 29 Oct 2021 13:12:12 +0000 | D1108: 29 | E1108: 10 | F1108: 2021 | G1108: 44498 | H1108: 6 | I1108: Empreendedor 81 | J1108: Empreendedor | K1108: 81 | L1108: =G1108-G1107 -> 3
A1109: Título: NerdCast 801 - Pelados e apavorados - | B1109: https://jovemnerd.com.br/nerdcast/pelados-e-apavorados/ | C1109: Fri, 29 Oct 2021 13:16:07 +0000 | D1109: 29 | E1109: 10 | F1109: 2021 | G1109: 44498 | H1109: 6 | I1109: NerdCast 801 | J1109: NerdCast | K1109: 801 | L1109: =G1109-G1108 -> 0
A1110: Título: Caneca de Mamicas 26 - Antes só do que mal assombrado - | B1110: https://jovemnerd.com.br/nerdcast/caneca-de-mamicas/antes-so-do-que-mal-assombrado/ | C1110: Sat, 30 Oct 2021 11:00:24 +0000 | D1110: 30 | E1110: 10 | F1110: 2021 | G1110: 44499 | H1110: 7 | I1110: Caneca de Mamicas 26 | J1110: Caneca de Mamicas | K1110: 26 | L1110: =G1110-G1109 -> 1
A1111: Título: Lá do Bunker 14 - Paladino estonteante e sensual - | B1111: https://jovemnerd.com.br/nerdcast/la-do-bunker/paladino-estonteante-e-sensual/ | C1111: Mon, 01 Nov 2021 06:00:02 +0000 | D1111: 01 | E1111: 11 | F1111: 2021 | G1111: 44501 | H1111: 2 | I1111: Lá do Bunker 14 | J1111: Lá do Bunker | K1111: 14 | L1111: =G1111-G1110 -> 2
A1112: Título: NerdCast 802 - Round 6: Não sabe brincar vai morrer no play - | B1112: https://jovemnerd.com.br/nerdcast/round-6-nao-sabe-brincar-vai-morrer-no-play/ | C1112: Fri, 05 Nov 2021 11:06:58 +0000 | D1112: 05 | E1112: 11 | F1112: 2021 | G1112: 44505 | H1112: 6 | I1112: NerdCast 802 | J1112: NerdCast | K1112: 802 | L1112: =G1112-G1111 -> 4
A1113: Título: NerdTech 69 - O tropeço na tomada das redes sociais - | B1113: https://jovemnerd.com.br/nerdcast/nerdtech/o-tropeco-na-tomada-das-redes-sociais/ | C1113: Fri, 05 Nov 2021 11:02:38 +0000 | D1113: 05 | E1113: 11 | F1113: 2021 | G1113: 44505 | H1113: 6 | I1113: NerdTech 69 | J1113: NerdTech | K1113: 69 | L1113: =G1113-G1112 -> 0
A1114: Título: Caneca de Mamicas 27 - Mais vale um padre no porão do que dois capirotos voando - | B1114: https://jovemnerd.com.br/nerdcast/caneca-de-mamicas/mais-vale-um-padre-no-porao-do-que-dois-capirotos-voando/ | C1114: Sat, 06 Nov 2021 11:00:37 +0000 | D1114: 06 | E1114: 11 | F1114: 2021 | G1114: 44506 | H1114: 7 | I1114: Caneca de Mamicas 27 | J1114: Caneca de Mamicas | K1114: 27 | L1114: =G1114-G1113 -> 1
A1115: Título: Lá do Bunker 15 - Questionando a vida real - | B1115: https://jovemnerd.com.br/nerdcast/la-do-bunker/questionando-a-vida-real/ | C1115: Mon, 08 Nov 2021 06:00:53 +0000 | D1115: 08 | E1115: 11 | F1115: 2021 | G1115: 44508 | H1115: 2 | I1115: Lá do Bunker 15 | J1115: Lá do Bunker | K1115: 15 | L1115: =G1115-G1114 -> 2
A1116: Título: Extra Oferecido por Arcane: League of Legends - Arcane – Ato I: Ciência e Magia - | B1116: https://jovemnerd.com.br/nerdcast/extra/arcane-ato-i-ciencia-e-magia/ | C1116: Tue, 09 Nov 2021 14:48:14 +0000 | D1116: 09 | E1116: 11 | F1116: 2021 | G1116: 44509 | H1116: 3 | I1116: Extra Oferecido por Arcane: League of Legends | J1116: Extra Oferecido por Arcane: League of Legends | L1116: =G1116-G1115 -> 1
A1117: Título: NerdCash 41 - Câmbio Bipolar - | B1117: https://jovemnerd.com.br/nerdcast/nerdcash/cambio-bipolar/ | C1117: Fri, 12 Nov 2021 14:12:37 +0000 | D1117: 12 | E1117: 11 | F1117: 2021 | G1117: 44512 | H1117: 6 | I1117: NerdCash 41 | J1117: NerdCash | K1117: 41 | L1117: =G1117-G1116 -> 3
A1118: Título: NerdCast 803 - Em Duna o choro não é livre - | B1118: https://jovemnerd.com.br/nerdcast/em-duna-o-choro-nao-e-livre/ | C1118: Fri, 12 Nov 2021 14:14:33 +0000 | D1118: 12 | E1118: 11 | F1118: 2021 | G1118: 44512 | H1118: 6 | I1118: NerdCast 803 | J1118: NerdCast | K1118: 803 | L1118: =G1118-G1117 -> 0
A1119: Título: Caneca de Mamicas 28 - Use a lupa e encontre o limite - | B1119: https://jovemnerd.com.br/nerdcast/caneca-de-mamicas/use-a-lupa-e-encontre-o-limite/ | C1119: Sat, 13 Nov 2021 11:00:25 +0000 | D1119: 13 | E1119: 11 | F1119: 2021 | G1119: 44513 | H1119: 7 | I1119: Caneca de Mamicas 28 | J1119: Caneca de Mamicas | K1119: 28 | L1119: =G1119-G1118 -> 1
A1120: Título: Lá do Bunker 16 - Homem-Aranha: emo ou gótico suave? - | B1120: https://jovemnerd.com.br/nerdcast/la-do-bunker/homem-aranha-emo-ou-gotico-suave/ | C1120: Mon, 15 Nov 2021 06:00:06 +0000 | D1120: 15 | E1120: 11 | F1120: 2021 | G1120: 44515 | H1120: 2 | I1120: Lá do Bunker 16 | J1120: Lá do Bunker | K1120: 16 | L1120: =G1120-G1119 -> 2
A1121: Título: Extra Oferecido por Arcane: League of Legends - Arcane – Ato II: Largados e Shippados - | B1121: https://jovemnerd.com.br/nerdcast/extra/arcane-ato-ii-largados-e-shippados/ | C1121: Tue, 16 Nov 2021 14:21:03 +0000 | D1121: 16 | E1121: 11 | F1121: 2021 | G1121: 44516 | H1121: 3 | I1121: Extra Oferecido por Arcane: League of Legends | J1121: Extra Oferecido por Arcane: League of Legends | L1121: =G1121-G1120 -> 1
A1122: Título: NerdCast 804 - Eternos e Shang-Chi: Imortais são babacas! - | B1122: https://jovemnerd.com.br/nerdcast/eternos-e-shang-chi-imortais-sao-babacas/ | C1122: Fri, 19 Nov 2021 14:09:55 +0000 | D1122: 19 | E1122: 11 | F1122: 2021 | G1122: 44519 | H1122: 6 | I1122: NerdCast 804 | J1122: NerdCast | K1122: 804 | L1122: =G1122-G1121 -> 3
A1123: Título: Speak English 45 - Frases Marcantes de Filmes e Séries em 2021 - | B1123: https://jovemnerd.com.br/nerdcast/speak-english/frases-marcantes-de-filmes-e-series-em-2021/ | C1123: Fri, 19 Nov 2021 13:35:44 +0000 | D1123: 19 | E1123: 11 | F1123: 2021 | G1123: 44519 | H1123: 6 | I1123: Speak English 45 | J1123: Speak English | K1123: 45 | L1123: =G1123-G1122 -> 0
A1124: Título: Caneca de Mamicas 29 - Vale a pena cantar de novo - | B1124: https://jovemnerd.com.br/nerdcast/caneca-de-mamicas/vale-a-pena-cantar-de-novo/ | C1124: Sat, 20 Nov 2021 13:45:58 +0000 | D1124: 20 | E1124: 11 | F1124: 2021 | G1124: 44520 | H1124: 7 | I1124: Caneca de Mamicas 29 | J1124: Caneca de Mamicas | K1124: 29 | L1124: =G1124-G1123 -> 1
A1125: Título: Lá do Bunker 17 - Não é defeito, é efeito - | B1125: https://jovemnerd.com.br/nerdcast/la-do-bunker/nao-e-defeito-e-efeito/ | C1125: Mon, 22 Nov 2021 06:00:57 +0000 | D1125: 22 | E1125: 11 | F1125: 2021 | G1125: 44522 | H1125: 2 | I1125: Lá do Bunker 17 | J1125: Lá do Bunker | K1125: 17 | L1125: =G1125-G1124 -> 2
A1126: Título: Extra Oferecido por Arcane: League of Legends - Arcane – Ato III: Por que lutamos - | B1126: https://jovemnerd.com.br/nerdcast/extra/arcane-ato-iii-por-que-lutamos/ | C1126: Tue, 23 Nov 2021 15:18:56 +0000 | D1126: 23 | E1126: 11 | F1126: 2021 | G1126: 44523 | H1126: 3 | I1126: Extra Oferecido por Arcane: League of Legends | J1126: Extra Oferecido por Arcane: League of Legends | L1126: =G1126-G1125 -> 1
A1127: Título: Lá do Bunker 18 - Discorde aí de longe - | B1127: https://jovemnerd.com.br/nerdcast/la-do-bunker/discorde-ai-de-longe/ | C1127: Thu, 25 Nov 2021 06:00:55 +0000 | D1127: 25 | E1127: 11 | F1127: 2021 | G1127: 44525 | H1127: 5 | I1127: Lá do Bunker 18 | J1127: Lá do Bunker | K1127: 18 | L1127: =G1127-G1126 -> 2
A1128: Título: Empreendedor 82 - A história da Alura - | B1128: https://jovemnerd.com.br/nerdcast/empreendedor/a-historia-da-alura/ | C1128: Fri, 26 Nov 2021 11:49:32 +0000 | D1128: 26 | E1128: 11 | F1128: 2021 | G1128: 44526 | H1128: 6 | I1128: Empreendedor 82 | J1128: Empreendedor | K1128: 82 | L1128: =G1128-G1127 -> 1
A1129: Título: NerdCast 805 - Magias do RPG: Da bola de fogo à aposentadoria - | B1129: https://jovemnerd.com.br/nerdcast/magias-do-rpg-da-bola-de-fogo-a-aposentadoria/ | C1129: Fri, 26 Nov 2021 12:24:41 +0000 | D1129: 26 | E1129: 11 | F1129: 2021 | G1129: 44526 | H1129: 6 | I1129: NerdCast 805 | J1129: NerdCast | K1129: 805 | L1129: =G1129-G1128 -> 0
A1130: Título: Caneca de Mamicas 30 - Credo de novela que limite delícia - | B1130: https://jovemnerd.com.br/nerdcast/caneca-de-mamicas/credo-de-novela-que-limite-delicia/ | C1130: Sat, 27 Nov 2021 11:46:59 +0000 | D1130: 27 | E1130: 11 | F1130: 2021 | G1130: 44527 | H1130: 7 | I1130: Caneca de Mamicas 30 | J1130: Caneca de Mamicas | K1130: 30 | L1130: =G1130-G1129 -> 1
A1131: Título: Lá do Bunker 19 - Necessário, cirúrgico, preciso - | B1131: https://jovemnerd.com.br/nerdcast/la-do-bunker/necessario-cirurgico-preciso/ | C1131: Mon, 29 Nov 2021 06:00:16 +0000 | D1131: 29 | E1131: 11 | F1131: 2021 | G1131: 44529 | H1131: 2 | I1131: Lá do Bunker 19 | J1131: Lá do Bunker | K1131: 19 | L1131: =G1131-G1130 -> 2
A1132: Título: Papo de Parceiro 04 - A logística e a correria da Black Friday - | B1132: https://jovemnerd.com.br/nerdcast/papo-de-parceiro/a-logistica-e-a-correria-da-black-friday/ | C1132: Tue, 30 Nov 2021 13:43:30 +0000 | D1132: 30 | E1132: 11 | F1132: 2021 | G1132: 44530 | H1132: 3 | I1132: Papo de Parceiro 04 | J1132: Papo de Parceiro | K1132: 04 | L1132: =G1132-G1131 -> 1
A1133: Título: NerdCast 806 - Fundação: Bom dia, boa tarde e boa noite - | B1133: https://jovemnerd.com.br/nerdcast/fundacao-bom-dia-boa-tarde-e-boa-noite/ | C1133: Fri, 03 Dec 2021 13:50:58 +0000 | D1133: 03 | E1133: 12 | F1133: 2021 | G1133: 44533 | H1133: 6 | I1133: NerdCast 806 | J1133: NerdCast | K1133: 806 | L1133: =G1133-G1132 -> 3
A1134: Título: NerdTech 70 - Desdobrando o Metaverso - | B1134: https://jovemnerd.com.br/nerdcast/nerdtech/desdobrando-o-metaverso/ | C1134: Fri, 03 Dec 2021 13:01:19 +0000 | D1134: 03 | E1134: 12 | F1134: 2021 | G1134: 44533 | H1134: 6 | I1134: NerdTech 70 | J1134: NerdTech | K1134: 70 | L1134: =G1134-G1133 -> 0
A1135: Título: Caneca de Mamicas 31 - Botox Party - | B1135: https://jovemnerd.com.br/nerdcast/caneca-de-mamicas/botox-party/ | C1135: Sat, 04 Dec 2021 11:41:56 +0000 | D1135: 04 | E1135: 12 | F1135: 2021 | G1135: 44534 | H1135: 7 | I1135: Caneca de Mamicas 31 | J1135: Caneca de Mamicas | K1135: 31 | L1135: =G1135-G1134 -> 1
A1136: Título: Lá do Bunker 20 - Câmera lenta é amor - | B1136: https://jovemnerd.com.br/nerdcast/la-do-bunker/camera-lenta-e-amor/ | C1136: Mon, 06 Dec 2021 06:00:58 +0000 | D1136: 06 | E1136: 12 | F1136: 2021 | G1136: 44536 | H1136: 2 | I1136: Lá do Bunker 20 | J1136: Lá do Bunker | K1136: 20 | L1136: =G1136-G1135 -> 2
A1137: Título: Extra Oferecido por Fanta - CCXP: Bastidores, Perrengues e o Penetra - | B1137: https://jovemnerd.com.br/nerdcast/extra/ccxp-bastidores-perrengues-e-o-penetra/ | C1137: Tue, 07 Dec 2021 14:07:03 +0000 | D1137: 07 | E1137: 12 | F1137: 2021 | G1137: 44537 | H1137: 3 | I1137: Extra Oferecido por Fanta | J1137: Extra Oferecido por Fanta | L1137: =G1137-G1136 -> 1
A1138: Título: Lá do Bunker Oferecido por Fanta - Extra: CCXP Worlds 2021 - | B1138: https://jovemnerd.com.br/nerdcast/la-do-bunker/extra-ccxp-worlds-2021/ | C1138: Thu, 09 Dec 2021 06:00:18 +0000 | D1138: 09 | E1138: 12 | F1138: 2021 | G1138: 44539 | H1138: 5 | I1138: Lá do Bunker Oferecido por Fanta | J1138: Lá do Bunker Oferecido por Fanta | L1138: =G1138-G1137 -> 2
A1139: Título: NerdCash 42 - A economia em 2021 - | B1139: https://jovemnerd.com.br/nerdcast/nerdcash/a-economia-em-2021/ | C1139: Fri, 10 Dec 2021 13:14:23 +0000 | D1139: 10 | E1139: 12 | F1139: 2021 | G1139: 44540 | H1139: 6 | I1139: NerdCash 42 | J1139: NerdCash | K1139: 42 | L1139: =G1139-G1138 -> 1
A1140: Título: NerdCast 807 - David Bowie: As múltiplas faces de um artista único - | B1140: https://jovemnerd.com.br/nerdcast/david-bowie-as-multiplas-faces-de-um-artista-unico/ | C1140: Fri, 10 Dec 2021 14:06:45 +0000 | D1140: 10 | E1140: 12 | F1140: 2021 | G1140: 44540 | H1140: 6 | I1140: NerdCast 807 | J1140: NerdCast | K1140: 807 | L1140: =G1140-G1139 -> 0
A1141: Título: Caneca de Mamicas 32 - O melhor padrão é ser feliz - | B1141: https://jovemnerd.com.br/nerdcast/caneca-de-mamicas/o-melhor-padrao-e-ser-feliz/ | C1141: Sat, 11 Dec 2021 11:29:29 +0000 | D1141: 11 | E1141: 12 | F1141: 2021 | G1141: 44541 | H1141: 7 | I1141: Caneca de Mamicas 32 | J1141: Caneca de Mamicas | K1141: 32 | L1141: =G1141-G1140 -> 1
A1142: Título: Lá do Bunker 21 - Muito bom, nota zero - | B1142: https://jovemnerd.com.br/nerdcast/la-do-bunker/muito-bom-nota-zero/ | C1142: Mon, 13 Dec 2021 06:00:00 +0000 | D1142: 13 | E1142: 12 | F1142: 2021 | G1142: 44543 | H1142: 2 | I1142: Lá do Bunker 21 | J1142: Lá do Bunker | K1142: 21 | L1142: =G1142-G1141 -> 2
A1143: Título: NerdCast 808 - Profissão: Indie Game Dev - | B1143: https://jovemnerd.com.br/nerdcast/profissao-indie-game-dev/ | C1143: Fri, 17 Dec 2021 13:12:59 +0000 | D1143: 17 | E1143: 12 | F1143: 2021 | G1143: 44547 | H1143: 6 | I1143: NerdCast 808 | J1143: NerdCast | K1143: 808 | L1143: =G1143-G1142 -> 4
A1144: Título: Speak English 46 - Inglês traduzido ao pé da letra - | B1144: https://jovemnerd.com.br/nerdcast/speak-english/ingles-traduzido-ao-pe-da-letra/ | C1144: Fri, 17 Dec 2021 11:26:12 +0000 | D1144: 17 | E1144: 12 | F1144: 2021 | G1144: 44547 | H1144: 6 | I1144: Speak English 46 | J1144: Speak English | K1144: 46 | L1144: =G1144-G1143 -> 0
...

Sheet NerdCasts
A1: Episódios do NerdCast: | B1: Link | C1: Data | D1: Dia | E1: Mês | F1: Ano | G1: DT Data | H1: Data Semana | I1: Tipo + Episódio | J1: Tipo | K1: # Episódio | L1: Dif Data
A2: Título: NerdCast 01 - Super-Homem: Herói americano ou do mundo? - | B2: =VLOOKUP(A2,BASE!$A:$B,2,FALSE) -> https://jovemnerd.com.br/nerdcast/01-super-homem-heroi-americando-ou-do-mundo/ | C2: Sun, 02 Apr 2006 17:39:39 +0000 | D2: 02 | E2: 4 | F2: 2006 | G2: 38809 | H2: 1 | I2: NerdCast 01 | J2: NerdCast | K2: 01 | L2: 0
A3: Título: NerdCast 02 - Batman Continues: Quem serão os vilões? - | B3: =VLOOKUP(A3,BASE!$A:$B,2,FALSE) -> https://jovemnerd.com.br/nerdcast/02-batman-continues-quem-serao-os-viloes/ | C3: Sun, 02 Apr 2006 17:43:22 +0000 | D3: 02 | E3: 4 | F3: 2006 | G3: 38809 | H3: 1 | I3: NerdCast 02 | J3: NerdCast | K3: 02 | L3: =G3-G2 -> 0
A4: Título: NerdCast 03 - Quadrinhos: A volta de Jason Todd (?!) - | B4: =VLOOKUP(A4,BASE!$A:$B,2,FALSE) -> https://jovemnerd.com.br/nerdcast/03-quadrinhos-a-volta-de-jason-todd/ | C4: Sun, 02 Apr 2006 17:46:32 +0000 | D4: 02 | E4: 4 | F4: 2006 | G4: 38809 | H4: 1 | I4: NerdCast 03 | J4: NerdCast | K4: 03 | L4: =G4-G3 -> 0
A5: Título: NerdCast 04 - Rocky Balboa está de volta: comemorar ou chorar? - | B5: =VLOOKUP(A5,BASE!$A:$B,2,FALSE) -> https://jovemnerd.com.br/nerdcast/04-rocky-balboa-esta-de-volta-comemorar-ou-chorar/ | C5: Sun, 02 Apr 2006 17:47:44 +0000 | D5: 02 | E5: 4 | F5: 2006 | G5: 38809 | H5: 1 | I5: NerdCast 04 | J5: NerdCast | K5: 04 | L5: =G5-G4 -> 0
A6: Título: NerdCast 05 - Bárbaros, Exterminadores e uma Vareta Espacial - | B6: =VLOOKUP(A6,BASE!$A:$B,2,FALSE) -> https://jovemnerd.com.br/nerdcast/nerdcast-05-barbaros-exterminadores-e-uma-vareta-espacial/ | C6: Sun, 02 Apr 2006 19:19:01 +0000 | D6: 02 | E6: 4 | F6: 2006 | G6: 38809 | H6: 1 | I6: NerdCast 05 | J6: NerdCast | K6: 05 | L6: =G6-G5 -> 0
A7: Título: NerdCast 06 - V de Vingança - | B7: =VLOOKUP(A7,BASE!$A:$B,2,FALSE) -> https://jovemnerd.com.br/nerdcast/nerdcast-06-v-de-vinganca/ | C7: Sat, 08 Apr 2006 17:11:14 +0000 | D7: 08 | E7: 4 | F7: 2006 | G7: 38815 | H7: 7 | I7: NerdCast 06 | J7: NerdCast | K7: 06 | L7: =G7-G6 -> 6
A8: Título: NerdCast 07 - Os brucutus dos anos 80 - | B8: =VLOOKUP(A8,BASE!$A:$B,2,FALSE) -> https://jovemnerd.com.br/nerdcast/nerdcast-07-os-brucutus-dos-anos-80/ | C8: Tue, 11 Apr 2006 01:32:49 +0000 | D8: 11 | E8: 4 | F8: 2006 | G8: 38818 | H8: 3 | I8: NerdCast 07 | J8: NerdCast | K8: 07 | L8: =G8-G7 -> 3
A9: Título: NerdCast 08 - O Poderoso Chefão - | B9: =VLOOKUP(A9,BASE!$A:$B,2,FALSE) -> https://jovemnerd.com.br/nerdcast/nerdcast-08-o-poderoso-chefao/ | C9: Tue, 18 Apr 2006 00:57:31 +0000 | D9: 18 | E9: 4 | F9: 2006 | G9: 38825 | H9: 3 | I9: NerdCast 08 | J9: NerdCast | K9: 08 | L9: =G9-G8 -> 7
A10: Título: NerdCast 09 - Pérolas do RPG - | B10: =VLOOKUP(A10,BASE!$A:$B,2,FALSE) -> https://jovemnerd.com.br/nerdcast/nerdcast-09-perolas-do-rpg/ | C10: Fri, 21 Apr 2006 14:15:39 +0000 | D10: 21 | E10: 4 | F10: 2006 | G10: 38828 | H10: 6 | I10: NerdCast 09 | J10: NerdCast | K10: 09 | L10: =G10-G9 -> 3
A11: Título: NerdCast 10 - Nostalgia Tecnológica - | B11: =VLOOKUP(A11,BASE!$A:$B,2,FALSE) -> https://jovemnerd.com.br/nerdcast/nerdcast-10-nostalgia-tecnologica/ | C11: Fri, 28 Apr 2006 03:24:55 +0000 | D11: 28 | E11: 4 | F11: 2006 | G11: 38835 | H11: 6 | I11: NerdCast 10 | J11: NerdCast | K11: 10 | L11: =G11-G10 -> 7
A12: Título: NerdCast 11 - Missão: Nerdcast - | B12: =VLOOKUP(A12,BASE!$A:$B,2,FALSE) -> https://jovemnerd.com.br/nerdcast/nerdcast-11-missao-nerdcast/ | C12: Sun, 07 May 2006 23:44:26 +0000 | D12: 07 | E12: 5 | F12: 2006 | G12: 38844 | H12: 1 | I12: NerdCast 11 | J12: NerdCast | K12: 11 | L12: =G12-G11 -> 9
A13: Título: NerdCast 12 - Os primórdios dos vídeo games - | B13: =VLOOKUP(A13,BASE!$A:$B,2,FALSE) -> https://jovemnerd.com.br/nerdcast/nerdcast-12-os-primordios-dos-video-games/ | C13: Thu, 11 May 2006 02:19:04 +0000 | D13: 11 | E13: 5 | F13: 2006 | G13: 38848 | H13: 5 | I13: NerdCast 12 | J13: NerdCast | K13: 12 | L13: =G13-G12 -> 4
A14: Título: NerdCast 13 - Google é meu pastor e nada me faltará - | B14: =VLOOKUP(A14,BASE!$A:$B,2,FALSE) -> https://jovemnerd.com.br/nerdcast/nerdcast-13-google-e-meu-pastor-e-nada-me-faltara/ | C14: Wed, 17 May 2006 01:47:02 +0000 | D14: 17 | E14: 5 | F14: 2006 | G14: 38854 | H14: 4 | I14: NerdCast 13 | J14: NerdCast | K14: 13 | L14: =G14-G13 -> 6
... A978: Título: NerdCast 963 - Qual é a pauta? Cabide de esteira, whey e Cindy Lauper - | B978: =VLOOKUP(A978,BASE!$A:$B,2,FALSE) -> https://jovemnerd.com.br/nerdcast/qual-e-a-pauta-cabide-de-esteira-whey-e-cindy-lauper/ | C978: Fri, 20 Dec 2024 12:19:49 +0000 | D978: 20 | E978: 12 | F978: 2024 | G978: 45646 | H978: 6 | I978: NerdCast 963 | J978: NerdCast | K978: 963 | L978: =G978-G977 -> 7
G979: =TODAY() -> 45852 | L979: =G979-G978 -> 206

Sheet Página10
A2: Chegamos ao Top 3 Maior período sem NerdCast
A4: Hoje (06/Jan) fazem 17 dias desde a última publicação de um NerdCast
A6: Fiquei na dúvida sobre quão raro é não ter nenhum NerdCast na semana
A8: Então eu levantei as datas de publicação do feed RSS para todos os Ep de NerdCast (que contam para a sequência de 963 ep*) cheguei aos seguintes números:
A10: Os dois maiores hiatos entre episódios foram de 21 dias, nos ep 193 e 292 - ambos publicados em Janeiro, após o recesso de fim de ano (2010 e 2012).
A11: O terceiro maior hiato foi de 17 dias, ep 113b - lá em 2008. Não sei se teve algum erro nessa publicação, pois está na mesma data do 114, e saíram em uma segunda-feira.
A12: Desde jan/2024 - ep 914 (Nerdcast RPG - 13d) e ep 915 (15d) - não havia hiatos. E antes disso o último foi em jan/2020 (ep 707) - também após recesso.
A13: Tirando o NC RPG Cyberpunk 3 e Ghanor 6, os ep de NC RPG não costumam "atrasar" (no sentido de ter um ep na sexta anterior), mas geralmente os ep após os NC RPG atrasam 1 a 2 semanas.
A14: Se considerar todo o histórico de NerdCasts (desde 2006), tem apenas 17 semanas em que a diferença entre publicações foi > 8 dias. Dá menos de 2% de atrasos.
A16: Os dados extraídos estão aqui caso alguém queira dar uma olhada: https://docs.google.com/spreadsheets/d/1KXQCnJx3ZR7lmobDtwgqCKs-gpL83bYcEiqyRtyNgL0/edit?usp=sharing
A18: O que isso significa? Nada, só quis dar meus parabéns ao trabalho desses caras. Esse nível de consistência com entrega é admirável!
A20: Obs: Tem 2 números repetidos na lista do feed referente a NerdCast, o 205 e o 241. Ambos tem 2 episódios cada associados a esse #, mas publicados em dias diferentes e temas diferentes. Considerando que tem vários ep com A e B, não faz diferença, mas se quiserem contestar qual será o verdadeiro ep 1000, fiquem à vontade
A22: Obs2: Eu ajustei episódios de Empreendedor para NerdCast pois estão listados na sequência dos NCs. Os que ganharam sequência própria ficaram fora dessa lista
